{
  "tag": "2020-03-15_001937",
  "event": {
    "event_type": "touch",
    "x": null,
    "y": null,
    "view": {
      "package": "org.quantumbadger.redreader",
      "visible": true,
      "checkable": false,
      "child_count": 1,
      "editable": false,
      "clickable": true,
      "is_password": false,
      "focusable": true,
      "enabled": true,
      "content_description": null,
      "children": [
        73
      ],
      "focused": false,
      "bounds": [
        [
          21,
          1743
        ],
        [
          1059,
          1794
        ]
      ],
      "resource_id": null,
      "checked": false,
      "text": null,
      "class": "android.widget.FrameLayout",
      "scrollable": false,
      "selected": false,
      "long_clickable": true,
      "parent": 17,
      "temp_id": 72,
      "size": "1038*51",
      "signature": "[class]android.widget.FrameLayout[resource_id]None[text]None[enabled,,]",
      "view_str": "aa6aae5245a8dae03a89c3fbb7ae15ae",
      "content_free_signature": "[class]android.widget.FrameLayout[resource_id]None"
    }
  },
  "start_state": "397f5f45164dadf9336848d00ee0ed39",
  "stop_state": "2a3ea3e511667f8197b76c981af52d67",
  "event_str": "TouchEvent(state=397f5f45164dadf9336848d00ee0ed39, view=aa6aae5245a8dae03a89c3fbb7ae15ae)"
}